.gitignore
LICENSE
README.md
setup.cfg
setup.py
./cbioportal/__init__.py
./cbioportal/create_cbioportal_database.py
./cbioportal/vcf_annotate_cbioportal.py
./cbioportal/test/__init__.py
./cbioportal/test/create_cbioportal_database_test.py
./utils/__init__.py
./utils/utils.py
cbioportal/__init__.py
cbioportal/create_cbioportal_database.py
cbioportal/vcf_annotate_cbioportal.py
cbioportal/test/__init__.py
cbioportal/test/create_cbioportal_database_test.py
iseqcbioportal.egg-info/PKG-INFO
iseqcbioportal.egg-info/SOURCES.txt
iseqcbioportal.egg-info/dependency_links.txt
iseqcbioportal.egg-info/entry_points.txt
iseqcbioportal.egg-info/requires.txt
iseqcbioportal.egg-info/top_level.txt
utils/__init__.py
utils/utils.py