Metadata-Version: 2.1
Name: iseqcbioportal
Version: 0.0.6
Summary: Package for creating database from cBioPortal and annotating VCF with information from this database
Home-page: https://gitlab.com/intelliseq/iseqcbioportal
Author: Mateusz Marynowski
Author-email: mateusz.marynowski@intelliseq.pl
Classifier: Programming Language :: Python :: 3
Classifier: License :: OSI Approved :: MIT License
Classifier: Operating System :: OS Independent
Requires-Python: >=3.6
License-File: LICENSE
